LICENSE.txt
MANIFEST.in
README.rst
TODO.txt
requirements-dev.txt
requirements.txt
setup.cfg
setup.py
tests/functional/test_proxy.py
tests/functional/test_screen.py
tests/functional/test_send_events.py
tests/functional/test_xvnc.py
tests/functional/data/example.png
tests/functional/data/example_nocursor.png
tests/functional/data/simple.png
tests/unit/test_client.py
tests/unit/test_command.py
tests/unit/test_rfb.py
vncdotool/__init__.py
vncdotool/api.py
vncdotool/client.py
vncdotool/command.py
vncdotool/loggingproxy.py
vncdotool/rfb.py
vncdotool.egg-info/PKG-INFO
vncdotool.egg-info/SOURCES.txt
vncdotool.egg-info/dependency_links.txt
vncdotool.egg-info/entry_points.txt
vncdotool.egg-info/requires.txt
vncdotool.egg-info/top_level.txt
vncdotool.egg-info/zip-safe