Metadata-Version: 2.1
Name: vncdotool
Version: 1.1.0
Summary: Command line VNC client
Home-page: http://github.com/sibson/vncdotool
Author: Marc Sibson
Author-email: sibson+vncdotool@gmail.com
License: MIT License
Keywords: VNC,RFB
Classifier: Development Status :: 4 - Beta
Classifier: Environment :: Console
Classifier: Framework :: Twisted
Classifier: Intended Audience :: Developers
Classifier: Intended Audience :: System Administrators
Classifier: License :: OSI Approved :: MIT License
Classifier: Operating System :: MacOS :: MacOS X
Classifier: Operating System :: Microsoft :: Windows
Classifier: Operating System :: POSIX
Classifier: Programming Language :: Python
Classifier: Programming Language :: Python :: 3.7
Classifier: Programming Language :: Python :: 3.8
Classifier: Programming Language :: Python :: 3.9
Classifier: Programming Language :: Python :: 3.10
Classifier: Programming Language :: Python :: 3.11
Classifier: Topic :: Multimedia :: Graphics :: Viewers
Classifier: Topic :: Software Development :: Testing
License-File: LICENSE.txt
